yapconf/__init__.py
yapconf/actions.py
yapconf/docs.py
yapconf/exceptions.py
yapconf/handlers.py
yapconf/items.py
yapconf/sources.py
yapconf/spec.py
yapconf-1.0.0.dist-info/AUTHORS.rst
yapconf-1.0.0.dist-info/LICENSE
yapconf-1.0.0.dist-info/METADATA
yapconf-1.0.0.dist-info/WHEEL
yapconf-1.0.0.dist-info/top_level.txt
yapconf-1.0.0.dist-info/RECORD
