Metadata-Version: 2.1
Name: yapconf
Version: 1.0.0
Summary: Yet Another Python Configuration
Home-page: https://github.com/loganasherjones/yapconf
Author: Logan Asher Jones
Author-email: loganasherjones@gmail.com
License: MIT license
Keywords: yapconf
Platform: UNKNOWN
Classifier: Development Status :: 4 - Beta
Classifier: Intended Audience :: Developers
Classifier: License :: OSI Approved :: MIT License
Classifier: Natural Language :: English
Classifier: Programming Language :: Python :: 2
Classifier: Programming Language :: Python :: 2.6
Classifier: Programming Language :: Python :: 2.7
Classifier: Programming Language :: Python :: 3
Classifier: Programming Language :: Python :: 3.5
Classifier: Programming Language :: Python :: 3.6
Classifier: Programming Language :: Python :: 3.7
Classifier: Programming Language :: Python :: 3.8
Classifier: Programming Language :: Python :: 3.9
Requires-Dist: six (<2)
Requires-Dist: python-box (<4)
Requires-Dist: watchdog (<1) ; python_version<"3.6"
Requires-Dist: watchdog (>1) ; python_version>"3.6"
Provides-Extra: deploy
Requires-Dist: wheel ; extra == 'deploy'
Requires-Dist: twine ; extra == 'deploy'
Provides-Extra: develop
Requires-Dist: isort ; extra == 'develop'
Requires-Dist: watchdog ; extra == 'develop'
Provides-Extra: docs
Requires-Dist: sphinx ; extra == 'docs'
Requires-Dist: sphinx-rtd-theme ; extra == 'docs'
Provides-Extra: etcd
Requires-Dist: python-etcd ; extra == 'etcd'
Provides-Extra: k8s
Requires-Dist: kubernetes ; extra == 'k8s'
Provides-Extra: test
Requires-Dist: codecov ; extra == 'test'
Requires-Dist: coverage ; extra == 'test'
Requires-Dist: flake8 ; extra == 'test'
Requires-Dist: funcsigs ; extra == 'test'
Requires-Dist: kubernetes ; extra == 'test'
Requires-Dist: mock ; extra == 'test'
Requires-Dist: pytest ; extra == 'test'
Requires-Dist: pytest-lazy-fixture ; extra == 'test'
Requires-Dist: pytest-cov ; extra == 'test'
Requires-Dist: pytest-runner ; extra == 'test'
Requires-Dist: python-etcd ; extra == 'test'
Requires-Dist: ruamel.yaml ; extra == 'test'
Requires-Dist: tox ; extra == 'test'
Provides-Extra: yaml
Requires-Dist: ruamel.yaml ; extra == 'yaml'
